{
  "gate": "structural_layout_guard",
  "passed": false,
  "checks": {
    "page_map_not_empty": true,
    "page_plan_not_empty": true,
    "page_plan_vs_page_map_exact_len": true,
    "technical_total_matches_page_map": true,
    "page_plan_contract_ok": true,
    "callouts_follow_page_plan": true,
    "pagination_model_ok": false
  },
  "contract_violations": [],
  "callouts": {
    "expected_from_page_plan": {},
    "found_in_page_map": {
      "callout_01": 18,
      "callout_02": 19,
      "callout_03": 20,
      "callout_04": 21,
      "callout_05": 22,
      "callout_06": 24
    },
    "violations": [],
    "warnings": []
  },
  "pagination_model": {
    "checks": {
      "first_page_is_cover": true,
      "second_page_is_blank": true,
      "third_page_is_toc": true,
      "toc_visible_numbering_matches_chapter_starts": false
    },
    "toc_mismatches": [
      {
        "index": 0,
        "toc_page": 4,
        "expected_visible_page": 2,
        "chapter_id": "ch_01",
        "chapter_physical_page": 4
      },
      {
        "index": 1,
        "toc_page": 6,
        "expected_visible_page": 4,
        "chapter_id": "ch_02",
        "chapter_physical_page": 6
      },
      {
        "index": 2,
        "toc_page": 18,
        "expected_visible_page": 16,
        "chapter_id": "ch_03",
        "chapter_physical_page": 18
      },
      {
        "index": 3,
        "toc_page": 21,
        "expected_visible_page": 19,
        "chapter_id": "ch_04",
        "chapter_physical_page": 21
      },
      {
        "index": 4,
        "toc_page": 23,
        "expected_visible_page": 21,
        "chapter_id": "epilogue",
        "chapter_physical_page": 23
      }
    ]
  }
}